{
  "version": 1,
  "data_dir": "C:\\Users\\k-yoneda\\Documents\\gyomu\\Data\\2026年3月\\大阪支社",
  "rows": [
    {
      "画像ファイル名": "[前半]ブライエ様_勤務表_山崎拓海_2603_2400397.png",
      "勤務先会社名": "（記載なし）",
      "氏名": "（記載なし）",
      "合計勤務時間（10進）": "88.08",
      "合計勤務時間（読取）": "88_05H",
      "押印有無": "無",
      "会社名比較（ファイル名✖文書）": "✖",
      "ユーザ判断": "✖",
      "resolved_path": "C:\\Users\\k-yoneda\\Documents\\gyomu\\Data\\2026年3月\\大阪支社\\[前半]ブライエ様_勤務表_山崎拓海_2603_2400397.png"
    },
    {
      "画像ファイル名": "[後半]ブライエ様_勤務表_山崎拓海_2603_2400397.png",
      "勤務先会社名": "記載なし（画像内で確認できず）",
      "氏名": "記載なし（画像内で確認できず）",
      "合計勤務時間（10進）": "86.16",
      "合計勤務時間（読取）": "86_10H",
      "押印有無": "無",
      "会社名比較（ファイル名✖文書）": "✖",
      "ユーザ判断": "✖",
      "resolved_path": "C:\\Users\\k-yoneda\\Documents\\gyomu\\Data\\2026年3月\\大阪支社\\[後半]ブライエ様_勤務表_山崎拓海_2603_2400397.png"
    },
    {
      "画像ファイル名": "[後半]ブライエ様_勤務表_永野浩暉_2603_2200637.png",
      "勤務先会社名": "（画像内に会社名の記載を確認できず）",
      "氏名": "永野浩暉",
      "合計勤務時間（10進）": "23.5",
      "合計勤務時間（読取）": "23_30H",
      "押印有無": "無",
      "会社名比較（ファイル名✖文書）": "✖",
      "ユーザ判断": "✖",
      "resolved_path": "C:\\Users\\k-yoneda\\Documents\\gyomu\\Data\\2026年3月\\大阪支社\\[後半]ブライエ様_勤務表_永野浩暉_2603_2200637.png"
    },
    {
      "画像ファイル名": "[押印無]CTCS様_勤務表_寺本雄次郎_2603_2300310.jpg",
      "勤務先会社名": "CTCSシステムマネジメント株式会社 大阪オフィス SD12（契約先コード / CTCS）",
      "氏名": "寺本 雄次郎",
      "合計勤務時間（10進）": "164.06",
      "合計勤務時間（読取）": "164時間4分",
      "押印有無": "無",
      "会社名比較（ファイル名✖文書）": "△",
      "ユーザ判断": "△",
      "resolved_path": "C:\\Users\\k-yoneda\\Documents\\gyomu\\Data\\2026年3月\\大阪支社\\[押印無]CTCS様_勤務表_寺本雄次郎_2603_2300310.jpg"
    },
    {
      "画像ファイル名": "[押印無]KSS様_作業報告書_黒野承太郎_2603_2300631.jpeg",
      "勤務先会社名": "不明",
      "氏名": "黒野 承太郎",
      "合計勤務時間（10進）": "164",
      "合計勤務時間（読取）": "164.00",
      "押印有無": "無",
      "会社名比較（ファイル名✖文書）": "✖",
      "ユーザ判断": "✖",
      "resolved_path": "C:\\Users\\k-yoneda\\Documents\\gyomu\\Data\\2026年3月\\大阪支社\\[押印無]KSS様_作業報告書_黒野承太郎_2603_2300631.jpeg"
    },
    {
      "画像ファイル名": "[押印無]NDSインフォス様_勤務表_中西麻衣_2603_2400407.jpeg",
      "勤務先会社名": "NDSインフォス株式会社",
      "氏名": "中西麻衣",
      "合計勤務時間（10進）": "165",
      "合計勤務時間（読取）": "165.00 H",
      "押印有無": "無",
      "会社名比較（ファイル名✖文書）": "〇",
      "ユーザ判断": "〇",
      "resolved_path": "C:\\Users\\k-yoneda\\Documents\\gyomu\\Data\\2026年3月\\大阪支社\\[押印無]NDSインフォス様_勤務表_中西麻衣_2603_2400407.jpeg"
    },
    {
      "画像ファイル名": "[押印無]NDSインフォス様_勤務表_大島佑太_2603_2500022.jpeg",
      "勤務先会社名": "NDSインフォス株式会社",
      "氏名": "大島 佑太",
      "合計勤務時間（10進）": "174.75",
      "合計勤務時間（読取）": "174.75H",
      "押印有無": "無",
      "会社名比較（ファイル名✖文書）": "〇",
      "ユーザ判断": "〇",
      "resolved_path": "C:\\Users\\k-yoneda\\Documents\\gyomu\\Data\\2026年3月\\大阪支社\\[押印無]NDSインフォス様_勤務表_大島佑太_2603_2500022.jpeg"
    },
    {
      "画像ファイル名": "[押印無]NDSインフォス様_勤務表_林将太_2603_1900464.jpeg",
      "勤務先会社名": "NDSインフォス株式会社",
      "氏名": "林将太",
      "合計勤務時間（10進）": "159",
      "合計勤務時間（読取）": "159.00 H",
      "押印有無": "無",
      "会社名比較（ファイル名✖文書）": "〇",
      "ユーザ判断": "〇",
      "resolved_path": "C:\\Users\\k-yoneda\\Documents\\gyomu\\Data\\2026年3月\\大阪支社\\[押印無]NDSインフォス様_勤務表_林将太_2603_1900464.jpeg"
    }
  ]
}